videoToImages/__init__.py
videoToImages/videoToImages.py
videoToImages-1.1.2.dist-info/LICENSE
videoToImages-1.1.2.dist-info/METADATA
videoToImages-1.1.2.dist-info/WHEEL
videoToImages-1.1.2.dist-info/entry_points.txt
videoToImages-1.1.2.dist-info/top_level.txt
videoToImages-1.1.2.dist-info/RECORD
