Metadata-Version: 2.1
Name: videoToImages
Version: 1.1.2
Summary: A easy to use, video to images converter
Home-page: https://github.com/aliwaqas333/VideoToImages
Author: Ali Waqas
Author-email: engrr.ali.waqas@gmail.com
License: UNKNOWN
Project-URL: Bug Tracker, https://github.com/aliwaqas333/VideoToImages/issues
Platform: UNKNOWN
Classifier: Programming Language :: Python :: 3
Classifier: License :: OSI Approved :: MIT License
Classifier: Operating System :: OS Independent
Requires-Python: >=3.6
License-File: LICENSE
